aiosecretsdump/__init__.py
aiosecretsdump/_version.py
aiosecretsdump/secretsdump.py
aiosecretsdump/domainsecrets/__init__.py
aiosecretsdump/domainsecrets/methods.py
aiosecretsdump/lsass/__init__.py
aiosecretsdump/lsass/methods.py
aiosecretsdump/lsass/utils.py
aiosecretsdump/registry/__init__.py
aiosecretsdump/registry/methods.py
bins/__init__.py
aiosecretsdump-0.0.2.dist-info/LICENSE
aiosecretsdump-0.0.2.dist-info/METADATA
aiosecretsdump-0.0.2.dist-info/WHEEL
aiosecretsdump-0.0.2.dist-info/entry_points.txt
aiosecretsdump-0.0.2.dist-info/top_level.txt
aiosecretsdump-0.0.2.dist-info/zip-safe
aiosecretsdump-0.0.2.dist-info/RECORD
